calligraph/__init__.py
calligraph/cli.py
calligraph/core.py
calligraph/geo.py
calligraph/pages.py
calligraph/plot.py
calligraph/ui.py
calligraph-0.1.1.dev7.dist-info/licenses/CITATION
calligraph-0.1.1.dev7.dist-info/licenses/LICENSE
calligraph-0.1.1.dev7.dist-info/METADATA
calligraph-0.1.1.dev7.dist-info/WHEEL
calligraph-0.1.1.dev7.dist-info/entry_points.txt
calligraph-0.1.1.dev7.dist-info/top_level.txt
calligraph-0.1.1.dev7.dist-info/RECORD
