Metadata-Version: 2.4
Name: calligraph
Version: 0.1.1.dev7
Summary: Visualisation tool for Calliope.
Author-email: Stefan Pfenninger <stefan@pfenninger.org>
Maintainer-email: Stefan Pfenninger <stefan@pfenninger.org>, Bryn Pickering <17178478+brynpickering@users.noreply.github.com>
License: Apache 2.0
Project-URL: website, https://www.callio.pe/
Project-URL: repository, https://github.com/calliope-project/calligraph
Project-URL: changelog, https://github.com/calliope-project/calligraph/CHANGELOG.md
Keywords: energy systems,visualisation
Classifier: Intended Audience :: Science/Research
Classifier: License :: OSI Approved :: Apache Software License
Classifier: Programming Language :: Python
Classifier: Programming Language :: Python :: 3
Classifier: Programming Language :: Python :: 3 :: Only
Requires-Python: >=3.10
License-File: LICENSE
License-File: CITATION
Requires-Dist: calliope>=0.7.0dev5
Requires-Dist: panel>=1.5.2
Requires-Dist: plotly>=5
Requires-Dist: pyproj>=3.6.1
Requires-Dist: click>=8.1
Dynamic: license-file
